cas_dev_server/__init__.py
cas_dev_server/internal/urls.py
cas_dev_server/internal/wsgi.py
cas_dev_server/internal/__init__.py
cas_dev_server/internal/settings.py
cas_dev_server/management/__init__.py
cas_dev_server/management/commands/__init__.py
cas_dev_server/management/commands/casdevmanage.py
cas_dev_server/management/commands/runserver.py
django_cas_dev_server-0.1.2.dist-info/METADATA
django_cas_dev_server-0.1.2.dist-info/RECORD
django_cas_dev_server-0.1.2.dist-info/top_level.txt
django_cas_dev_server-0.1.2.dist-info/DESCRIPTION.rst
django_cas_dev_server-0.1.2.dist-info/WHEEL
django_cas_dev_server-0.1.2.dist-info/metadata.json
