Metadata-Version: 2.0
Name: django-cas-dev-server
Version: 0.1.2
Summary: Extends the Django development server to include a local CAS server.
Home-page: https://github.com/TaymonB/django-cas-dev-server
Author: Taymon A. Beal
Author-email: taymonbeal@gmail.com
License: MIT
Keywords: cas development django
Platform: OS Independent
Classifier: Development Status :: 3 - Alpha
Classifier: Environment :: Console
Classifier: Framework :: Django
Classifier: Intended Audience :: Developers
Classifier: License :: OSI Approved :: MIT License
Classifier: Operating System :: OS Independent
Classifier: Programming Language :: Python :: 2
Classifier: Programming Language :: Python :: 2.7
Classifier: Programming Language :: Python :: 3
Classifier: Programming Language :: Python :: 3.2
Classifier: Programming Language :: Python :: 3.3
Classifier: Programming Language :: Python :: 3.4
Classifier: Topic :: Internet :: WWW/HTTP :: HTTP Servers
Classifier: Topic :: Software Development
Requires-Dist: Django (>=1.7)
Requires-Dist: django-environ
Requires-Dist: django-mama-cas
